example/__init__.py
example/example_code.py
tests/__init__.py
tests/tests.py
Example_Project-0.2.1.dist-info/LICENSE.txt
Example_Project-0.2.1.dist-info/METADATA
Example_Project-0.2.1.dist-info/WHEEL
Example_Project-0.2.1.dist-info/top_level.txt
Example_Project-0.2.1.dist-info/RECORD
