Metadata-Version: 2.1
Name: Example-Project
Version: 0.2.1
Summary: An example Python project
Home-page: https://github.com/Hakonmh/example-project
Author: Håkon Magne Holmen
Author-email: haakonholmen@outlook.com
License: MIT
Project-URL: Funding, https://donate.pypi.org
Project-URL: Documentation, https://an-example-project.readthedocs.io/en/latest/index.html
Keywords: sample development
Platform: UNKNOWN
Classifier: Development Status :: 3 - Alpha
Classifier: License :: OSI Approved :: MIT License
Classifier: Programming Language :: Python :: 3.6
Classifier: Programming Language :: Python :: 3.7
Requires-Python: >=3.6
